spark_exchange_rate_api/__init__.py
spark_exchange_rate_api/pyxr.py
spark_exchange_rate_api-0.1.2.dist-info/METADATA
spark_exchange_rate_api-0.1.2.dist-info/WHEEL
spark_exchange_rate_api-0.1.2.dist-info/top_level.txt
spark_exchange_rate_api-0.1.2.dist-info/RECORD
