Metadata-Version: 2.1
Name: spark-exchange-rate-api
Version: 0.1.2
Summary: A Python wrapper for exchangeratesapi.io developed by the Spark Tech team ⭐️
Home-page: https://github.com/Spark-Data-Team/spark-exchange-rate-api
Author: Larry Page
Author-email: tech@spark.do
Classifier: Programming Language :: Python :: 3
Classifier: License :: OSI Approved :: MIT License
Classifier: Operating System :: OS Independent
Requires-Dist: requests
Requires-Dist: datetime
